CHANGES.txt
LICENSE.txt
MANIFEST.in
README.md
setup.py
docs/index.rst
pwmanager/__init__.py
pwmanager/pwconfig.py
pwmanager/settings.py
pwmanager/urls.py
pwmanager/wsgi.py
pwmanager/nodes/__init__.py
pwmanager/nodes/admin.py
pwmanager/nodes/models.py
pwmanager/nodes/tests.py
pwmanager/nodes/views.py
pwmanager/nodes/templates/group.html
pwmanager/nodes/templates/home.html
pwmanager/static/pwmanager/css/main.css
pwmanager/static/pwmanager/js/app.coffee
pwmanager/static/pwmanager/js/app.js
pwmanager/static/pwmanager/js/app.map
pwmanager/static/pwmanager/js/app/message.coffee
pwmanager/static/pwmanager/js/app/message.js
pwmanager/static/pwmanager/js/app/message.map
pwmanager/static/pwmanager/js/app/node_.coffee
pwmanager/static/pwmanager/js/app/node_.js
pwmanager/static/pwmanager/js/app/node_.map
pwmanager/static/pwmanager/js/app/tab.coffee
pwmanager/static/pwmanager/js/app/tab.js
pwmanager/static/pwmanager/js/app/tab.map
pwmanager/static/pwmanager/js/app/ui.coffee
pwmanager/static/pwmanager/js/app/ui.js
pwmanager/static/pwmanager/js/app/ui.map
pwmanager/static/pwmanager/js/app/view_model.coffee
pwmanager/static/pwmanager/js/app/view_model.js
pwmanager/static/pwmanager/js/app/view_model.map
pwmanager/static/pwmanager/js/lib/jquery.js
pwmanager/static/pwmanager/js/lib/knockout.js
pwmanager/static/pwmanager/js/lib/reconnecting-websocket.js
pwmanager/static/pwmanager/js/lib/require.js
pwmanager/static/pwmanager/js/lib/sammy.js
pwserver/__init__.py
pwserver/app.py
pwserver/collectd-plugin.py
pwserver/config.py
pwserver/host.py
pwserver/server.py
pwserver/templates/upstart-server.conf
pywizard_server.egg-info/PKG-INFO
pywizard_server.egg-info/SOURCES.txt
pywizard_server.egg-info/dependency_links.txt
pywizard_server.egg-info/requires.txt
pywizard_server.egg-info/top_level.txt
scripts/pywizard-server