Metadata-Version: 1.0
Name: pywizard-server
Version: 0.4.20
Summary: Server for pywizard.
Home-page: UNKNOWN
Author: Alex Rudakov
Author-email: ribozz@gmail.com
License: MIT
Platform: UNKNOWN
